CHANGES.txt
HotTamale.py
LICENSE.txt
MANIFEST.in
README.txt
setup.py
HotTamale.egg-info/PKG-INFO
HotTamale.egg-info/SOURCES.txt
HotTamale.egg-info/dependency_links.txt
HotTamale.egg-info/requires.txt
HotTamale.egg-info/top_level.txt
hottamale/__init__.py