Metadata-Version: 1.0
Name: HotTamale
Version: 0.1.1
Summary: Spiceworks ticket display and notifier.
Home-page: http://pypi.python.org/pypi/HotTamale/
Author: Kyle Ondy
Author-email: KyleOndy@gmail.com
License: LICENSE.txt
Platform: UNKNOWN
